torchviz/__init__.py
torchviz/dot.py
torchviz-0.0.2.dist-info/LICENSE
torchviz-0.0.2.dist-info/METADATA
torchviz-0.0.2.dist-info/WHEEL
torchviz-0.0.2.dist-info/top_level.txt
torchviz-0.0.2.dist-info/zip-safe
torchviz-0.0.2.dist-info/RECORD
