Metadata-Version: 2.1
Name: torchviz
Version: 0.0.2
Summary: A small package to create visualizations of PyTorch execution graphs
Home-page: https://github.com/pytorch/pytorchviz
Author: Sergey Zagoruyko
Author-email: sergey.zagoruyko@enpc.fr
License: BSD
License-File: LICENSE
Requires-Dist: torch
Requires-Dist: graphviz
